midas_pwdata/__init__.py
midas_pwdata/meta.py
midas_pwdata/module.py
midas_pwdata-2.0.0.dist-info/METADATA
midas_pwdata-2.0.0.dist-info/WHEEL
midas_pwdata-2.0.0.dist-info/licenses/LICENSE
midas_pwdata-2.0.0.dist-info/RECORD
