Metadata-Version: 2.4
Name: midas-pwdata
Version: 2.0.0
Summary: A Midas module for pv and wind datasets.
Project-URL: Documentation, https://midas-mosaik.gitlab.io/midas
Author-email: Stephan Balduin <stephan.balduin@offis.de>
License-File: LICENSE
Requires-Python: >=3.8
Requires-Dist: midas-powerseries>=2.0.0
Requires-Dist: wget
Provides-Extra: dev
Requires-Dist: build; extra == 'dev'
Requires-Dist: coverage; extra == 'dev'
Requires-Dist: pytest; extra == 'dev'
Requires-Dist: ruff; extra == 'dev'
Requires-Dist: twine; extra == 'dev'
